{
    "AX": {
        "error": 0.0041243197821159905, 
        "filter_outliers_dict": {
            "filter_outliers": true, 
            "iterations": 1, 
            "std_devs": 2
        }, 
        "fit": "average", 
        "value": 0.04526667064126238
    }, 
    "CDD": {
        "error": 4.036738651374324e-06, 
        "filter_outliers_dict": {
            "filter_outliers": true, 
            "iterations": 1, 
            "std_devs": 10
        }, 
        "fit": "average", 
        "value": 1.1259289070293266e-05
    }, 
    "H1": {
        "error": 0.0033320958707942013, 
        "filter_outliers_dict": {
            "filter_outliers": true, 
            "iterations": 1, 
            "std_devs": 2
        }, 
        "fit": "average", 
        "value": -0.043859392348596
    }, 
    "H2": {
        "error": 0.003834540024056131, 
        "filter_outliers_dict": {
            "filter_outliers": true, 
            "iterations": 1, 
            "std_devs": 2
        }, 
        "fit": "average", 
        "value": 0.07160877034064576
    }, 
    "L1": {
        "error": 0.0016504065464843839, 
        "filter_outliers_dict": {
            "filter_outliers": true, 
            "iterations": 1, 
            "std_devs": 2
        }, 
        "fit": "average", 
        "value": -0.0010721785627832226
    }, 
    "L2": {
        "error": 0.003856638985331523, 
        "filter_outliers_dict": {
            "filter_outliers": true, 
            "iterations": 1, 
            "std_devs": 2
        }, 
        "fit": "average", 
        "value": 0.1448121558810453
    }
}